srff.v
module srff(s,r,q,qb,clk);
	input s,r,clk;
	output q,qb;
	wire x,y;
	nand(a,s,clk);
	nand(b,r,clk);
	nand(q,a,qb);
	nand(qb,b,q);
endmodule

srff_tb.v
module testbench;
	reg s,r,clk;
	wire q,qb;
	srff uut(.r(r), .s(s), .clk(clk), .q(q), .qb(qb));
	initial
		begin 
			$monitor("s=%b, r=%b, clk=%b, q=%b, qb=%b", s,r,clk,q,qb);
			$dumpfile("srff.vcd");
			$dumpvars(0,testbench);
			s=0;r=0;clk=0;
			#100 s=0; r=1;
			#100 s=1; r=0;
			#100 s=1; r=1;
			#100 s=0; r=1;
	end
	always #50 clk = ~clk;
endmodule

srff.vcd
$date
	Wed Mar 23 12:09:59 2022
$end
$version
	Icarus Verilog
$end
$timescale
	1s
$end
$scope module testbench $end
$var wire 1 ! qb $end
$var wire 1 " q $end
$var reg 1 # clk $end
$var reg 1 $ r $end
$var reg 1 % s $end
$scope module uut $end
$var wire 1 & a $end
$var wire 1 ' b $end
$var wire 1 # clk $end
$var wire 1 " q $end
$var wire 1 ! qb $end
$var wire 1 $ r $end
$var wire 1 % s $end
$upscope $end
$upscope $end
$enddefinitions $end
#0
$dumpvars
1'
1&
0%
0$
0#
x"
x!
$end
#50
1#
#100
0#
1$
#150
0"
1!
0'
1#
#200
1'
0#
0$
1%
#250
0!
1"
0&
1#
#300
1&
0#
1$
#350
1!
0&
0'
1#
#400
0"
1'
1&
0#
0%
#450
0'
1#
#500
1'
0#
#550
0'
1#
#600
1'
0#
#650
0'
1#
#700
1'
0#
#750
0'
1#
#800
1'
0#
#850
0'
1#
#900
1'
0#
#950
0'
1#
#1000
1'
0#
#1050
0'
1#
#1100
1'
0#
#1150
0'
1#
#1200
1'
0#
#1250
0'
1#
#1300
1'
0#
#1350
0'
1#
#1400
1'
0#
#1450
0'
1#
#1500
1'
0#
#1550
0'
1#
#1600
1'
0#
#1650
0'
1#
#1700
1'
0#
#1750
0'
1#
#1800
1'
0#
#1850
0'
1#
#1900
1'
0#
#1950
0'
1#
#2000
1'
0#
#2050
0'
1#
#2100
1'
0#
#2150
0'
1#
#2200
1'
0#
#2250
0'
1#
#2300
1'
0#
#2350
0'
1#
#2400
1'
0#
#2450
0'
1#
#2500
1'
0#
#2550
0'
1#
#2600
1'
0#
#2650
0'
1#
#2700
1'
0#
#2750
0'
1#
#2800
1'
0#
#2850
0'
1#
#2900
1'
0#
#2950
0'
1#
#3000
1'
0#
#3050
0'
1#
#3100
1'
0#
#3150
0'
1#
#3200
1'
0#
#3250
0'
1#
#3300
1'
0#
#3350
0'
1#
#3400
1'
0#
#3450
0'
1#
#3500
1'
0#
#3550
0'
1#
#3600
1'
0#
#3650
0'
1#
#3700
1'
0#
#3750
0'
1#
#3800
1'
0#
#3850
0'
1#
#3900
1'
0#
#3950
0'
1#
#4000
1'
0#
#4050
0'
1#
#4100
1'
0#
#4150
0'
1#
#4200
1'
0#
#4250
0'
1#
#4300
1'
0#
#4350
0'
1#
#4400
1'
0#
#4450
0'
1#
#4500
1'
0#
#4550
0'
1#
#4600
1'
0#
#4650
0'
1#
#4700
1'
0#
#4750
0'
1#
#4800
1'
0#
#4850
0'
1#
#4900
1'
0#
#4950
0'
1#
#5000
1'
0#
#5050
0'
1#
#5100
1'
0#
#5150
0'
1#
#5200
1'
0#
#5250
0'
1#
#5300
1'
0#
#5350
0'
1#
#5400
1'
0#
#5450
0'
1#
#5500
1'
0#
#5550
0'
1#
#5600
1'
0#
#5650
0'
1#
#5700
1'
0#
#5750
0'
1#
#5800
1'
0#
#5850
0'
1#
#5900
1'
0#
#5950
0'
1#
#6000
1'
0#
#6050
0'
1#
#6100
1'
0#
#6150
0'
1#
#6200
1'
0#
#6250
0'
1#
#6300
1'
0#
#6350
0'
1#
#6400
1'
0#
#6450
0'
1#
#6500
1'
0#
#6550
0'
1#
#6600
1'
0#
#6650
0'
1#
#6700
1'
0#
#6750
0'
1#
#6800
1'
0#
#6850
0'
1#
#6900
1'
0#
#6950
0'
1#
#7000
1'
0#
#7050
0'
1#
#7100
1'
0#
#7150
0'
1#
#7200
1'
0#
#7250
0'
1#
#7300
1'
0#
#7350
0'
1#
#7400
1'
0#
#7450
0'
1#
#7500
1'
0#
#7550
0'
1#
#7600
1'
0#
#7650
0'
1#
#7700
1'
0#
#7750
0'
1#
#7800
1'
0#
#7850
0'
1#
#7900
1'
0#
#7950
0'
1#
#8000
1'
0#
#8050
0'
1#
#8100
1'
0#
#8150
0'
1#
#8200
1'
0#
#8250
0'
1#
#8300
1'
0#
#8350
0'
1#
#8400
1'
0#
#8450
0'
1#
#8500
1'
0#
#8550
0'
1#
#8600
1'
0#
#8650
0'
1#
#8700
1'
0#
#8750
0'
1#
#8800
1'
0#
#8850
0'
1#
#8900
1'
0#
#8950
0'
1#
#9000
1'
0#
#9050
0'
1#
#9100
1'
0#
#9150
0'
1#
#9200
1'
0#
#9250
0'
1#
#9300
1'
0#
#9350
0'
1#
#9400
1'
0#
#9450
0'
1#
#9500
1'
0#
#9550
0'
1#
#9600
1'
0#
#9650
0'
1#
#9700
1'
0#
#9750
0'
1#
#9800
1'
0#
#9850
0'
1#
#9900
1'
0#
#9950
0'
1#
#10000
1'
0#
#10050
0'
1#
#10100
1'
0#
#10150
0'
1#
#10200
1'
0#
#10250
0'
1#
#10300
1'
0#
#10350
0'
1#
#10400
1'
0#
#10450
0'
1#
#10500
1'
0#
#10550
0'
1#
#10600
1'
0#
#10650
0'
1#
#10700
1'
0#
#10750
0'
1#
#10800
1'
0#
#10850
0'
1#
#10900
1'
0#
#10950
0'
1#
#11000
1'
0#
#11050
0'
1#
#11100
1'
0#
#11150
0'
1#
#11200
1'
0#
#11250
0'
1#
#11300
1'
0#
#11350
0'
1#
#11400
1'
0#
#11450
0'
1#
#11500
1'
0#
#11550
0'
1#
#11600
1'
0#
#11650
0'
1#
#11700
1'
0#
#11750
0'
1#
#11800
1'
0#
#11850
0'
1#
#11900
1'
0#
#11950
0'
1#
#12000
1'
0#
#12050
0'
1#
#12100
1'
0#
#12150
0'
1#
#12200
1'
0#
#12250
0'
1#
#12300
1'
0#
#12350
0'
1#
#12400
1'
0#
#12450
0'
1#
#12500
1'
0#
#12550
0'
1#
#12600
1'
0#
#12650
0'
1#
#12700
1'
0#
#12750
0'
1#
#12800
1'
0#
#12850
0'
1#
#12900
1'
0#
#12950
0'
1#
#13000
1'
0#
#13050
0'
1#
#13100
1'
0#
#13150
0'
1#
#13200
1'
0#
#13250
0'
1#
#13300
1'
0#
#13350
0'
1#
#13400
1'
0#
#13450
0'
1#
#13500
1'
0#
#13550
0'
1#
#13600
1'
0#
#13650
0'
1#
#13700
1'
0#
#13750
0'
1#
#13800
1'
0#
#13850
0'
1#
#13900
1'
0#
#13950
0'
1#
#14000
1'
0#
#14050
0'
1#
#14100
1'
0#
#14150
0'
1#
#14200
1'
0#
#14250
0'
1#
#14300
1'
0#
#14350
0'
1#
#14400
1'
0#
#14450
0'
1#
#14500
1'
0#
#14550
0'
1#
#14600
1'
0#
#14650
0'
1#
#14700
1'
0#
#14750
0'
1#
#14800
1'
0#
#14850
0'
1#
#14900
1'
0#
#14950
0'
1#
#15000
1'
0#
#15050
0'
1#
#15100
1'
0#
#15150
0'
1#
#15200
1'
0#
#15250
0'
1#
#15300
1'
0#
#15350
0'
1#
#15400
1'
0#
#15450
0'
1#
#15500
1'
0#
#15550
0'
1#
#15600
1'
0#
#15650
0'
1#
#15700
1'
0#
#15750
0'
1#
#15800
1'
0#
#15850
0'
1#
#15900
1'
0#
#15950
0'
1#
#16000
1'
0#
#16050
0'
1#
#16100
1'
0#
#16150
0'
1#
#16200
1'
0#
#16250
0'
1#
#16300
1'
0#
#16350
0'
1#
#16400
1'
0#
#16450
0'
1#
#16500
1'
0#
#16550
0'
1#
#16600
1'
0#
#16650
0'
1#
#16700
1'
0#
#16750
0'
1#
#16800
1'
0#
#16850
0'
1#
#16900
1'
0#
#16950
0'
1#
#17000
1'
0#
#17050
0'
1#
#17100
1'
0#
#17150
0'
1#
#17200
1'
0#
#17250
0'
1#
#17300
1'
0#
#17350
0'
1#
#17400
1'
0#
#17450
0'
1#
#17500
1'
0#
#17550
0'
1#
#17600
1'
0#
#17650
0'
1#
#17700
1'
0#
#17750
0'
1#
#17800
1'
0#
#17850
0'
1#
#17900
1'
0#
#17950
0'
1#
#18000
1'
0#
#18050
0'
1#
#18100
1'
0#
#18150
0'
1#
#18200
1'
0#
#18250
0'
1#
#18300
1'
0#
#18350
0'
1#
#18400
1'
0#
#18450
0'
1#
#18500
1'
0#
#18550
0'
1#
#18600
1'
0#
#18650
0'
1#
#18700
1'
0#
#18750
0'
1#
#18800
1'
0#
#18850
0'
1#
#18900
1'
0#
#18950
0'
1#
#19000
1'
0#
#19050
0'
1#
#19100
1'
0#
#19150
0'
1#
#19200
1'
0#
#19250
0'
1#
#19300
1'
0#
#19350
0'
1#
#19400
1'
0#
#19450
0'
1#
#19500
1'
0#
#19550
0'
1#
#19600
1'
0#
#19650
0'
1#
#19700
1'
0#
#19750
0'
1#
#19800
1'
0#
#19850
0'
1#
#19900
1'
0#
#19950
0'
1#
#20000
1'
0#
#20050
0'
1#
#20100
1'
0#
#20150
0'
1#
#20200
1'
0#
#20250
0'
1#
#20300
1'
0#
#20350
0'
1#
#20400
1'
0#
#20450
0'
1#
#20500
1'
0#
#20550
0'
1#
#20600
1'
0#
#20650
0'
1#
#20700
1'
0#
#20750
0'
1#
#20800
1'
0#
#20850
0'
1#
#20900
1'
0#
#20950
0'
1#
#21000
1'
0#
#21050
0'
1#
#21100
1'
0#
#21150
0'
1#
#21200
1'
0#
#21250
0'
1#
#21300
1'
0#
#21350
0'
1#
#21400
1'
0#
#21450
0'
1#
#21500
1'
0#
#21550
0'
1#
#21600
1'
0#
#21650
0'
1#
#21700
1'
0#
#21750
0'
1#
#21800
1'
0#
#21850
0'
1#
#21900
1'
0#
#21950
0'
1#
#22000
1'
0#
#22050
0'
1#
#22100
1'
0#
#22150
0'
1#
#22200
1'
0#
#22250
0'
1#
#22300
1'
0#
#22350
0'
1#
#22400
1'
0#
#22450
0'
1#
#22500
1'
0#
#22550
0'
1#
#22600
1'
0#
#22650
0'
1#
#22700
1'
0#
#22750
0'
1#
#22800
1'
0#
#22850
0'
1#
#22900
1'
0#
#22950
0'
1#
#23000
1'
0#
#23050
0'
1#
#23100
1'
0#
#23150
0'
1#
#23200
1'
0#
#23250
0'
1#
#23300
1'
0#
#23350
0'
1#
#23400
1'
0#
#23450
0'
1#
#23500
1'
0#
#23550
0'
1#
#23600
1'
0#
#23650
0'
1#
#23700
1'
0#
#23750
0'
1#
#23800
1'
0#
#23850
0'
1#
#23900
1'
0#
#23950
0'
1#
#24000
1'
0#
#24050
0'
1#
#24100
1'
0#
#24150
0'
1#
#24200
1'
0#
#24250
0'
1#
#24300
1'
0#
#24350
0'
1#
#24400
1'
0#
#24450
0'
1#
#24500
1'
0#
#24550
0'
1#
#24600
1'
0#
#24650
0'
1#
#24700
1'
0#
#24750
0'
1#
#24800
1'
0#
#24850
0'
1#
#24900
1'
0#
#24950
0'
1#
#25000
1'
0#
#25050
0'
1#
#25100
1'
0#
#25150
0'
1#
#25200
1'
0#
#25250
0'
1#
#25300
1'
0#
#25350
0'
1#
#25400
1'
0#
#25450
0'
1#
#25500
1'
0#
#25550
0'
1#
#25600
1'
0#
#25650
0'
1#
#25700
1'
0#
#25750
0'
1#
#25800
1'
0#
#25850
0'
1#
#25900
1'
0#
#25950
0'
1#
#26000
1'
0#
#26050
0'
1#
#26100
1'
0#
#26150
0'
1#
#26200
1'
0#
#26250
0'
1#
#26300
1'
0#
#26350
0'
1#
#26400
1'
0#
#26450
0'
1#
#26500
1'
0#
#26550
0'
1#
#26600
1'
0#
#26650
0'
1#
#26700
1'
0#
#26750
0'
1#
#26800
1'
0#
#26850
0'
1#
#26900
1'
0#
#26950
0'
1#
#27000
1'
0#
#27050
0'
1#
#27100
1'
0#
#27150
0'
1#
#27200
1'
0#
#27250
0'
1#
#27300
1'
0#
#27350
0'
1#
#27400
1'
0#
#27450
0'
1#
#27500
1'
0#
#27550
0'
1#
#27600
1'
0#
#27650
0'
1#
#27700
1'
0#
#27750
0'
1#
#27800
1'
0#
#27850
0'
1#
#27900
1'
0#
#27950
0'
1#
#28000
1'
0#
#28050
0'
1#
#28100
1'
0#
#28150
0'
1#
#28200
1'
0#
#28250
0'
1#
#28300
1'
0#
#28350
0'
1#
#28400
1'
0#
#28450
0'
1#
#28500
1'
0#
#28550
0'
1#
#28600
1'
0#
#28650
0'
1#
#28700
1'
0#
#28750
0'
1#
#28800
1'
0#
#28850
0'
1#
#28900
1'
0#
#28950
0'
1#
#29000
1'
0#
#29050
0'
1#
#29100
1'
0#
#29150
0'
1#
#29200
1'
0#
#29250
0'
1#
#29300
1'
0#
#29350
0'
1#
#29400
1'
0#
#29450
0'
1#
#29500
1'
0#
#29550
0'
1#
#29600
1'
0#
#29650
0'
1#
#29700
1'
0#
#29750
0'
1#
#29800
1'
0#
#29850
0'
1#
#29900
1'
0#
#29950
0'
1#
#30000
1'
0#
#30050
0'
1#
#30100
1'
0#
#30150
0'
1#
#30200
1'
0#
#30250
0'
1#
#30300
1'
0#
#30350
0'
1#
#30400
1'
0#
#30450
0'
1#
#30500
1'
0#
#30550
0'
1#
#30600
1'
0#
#30650
0'
1#
#30700
1'
0#
#30750
0'
1#
#30800
1'
0#
#30850
0'
1#
#30900
1'
0#
#30950
0'
1#
#31000
1'
0#
#31050
0'
1#
#31100
1'
0#
#31150
0'
1#
#31200
1'
0#
#31250
0'
1#
#31300
1'
0#
#31350
0'
1#
#31400
1'
0#
#31450
0'
1#
#31500
1'
0#
#31550
0'
1#
#31600
1'
0#
#31650
0'
1#
#31700
1'
0#
#31750
0'
1#
#31800
1'
0#
#31850
0'
1#
#31900
1'
0#
#31950
0'
1#
#32000
1'
0#
#32050
0'
1#
#32100
1'
0#
#32150
0'
1#
#32200
1'
0#
#32250
0'
1#
#32300
1'
0#
#32350
0'
1#
#32400
1'
0#
#32450
0'
1#
#32500
1'
0#
#32550
0'
1#
#32600
1'
0#
#32650
0'
1#
#32700
1'
0#
#32750
0'
1#
#32800
1'
0#
#32850
0'
1#
#32900
1'
0#
#32950
0'
1#
#33000
1'
0#
#33050
0'
1#
#33100
1'
0#
#33150
0'
1#
#33200
1'
0#
#33250
0'
1#
#33300
1'
0#
#33350
0'
1#
#33400
1'
0#
#33450
0'
1#
#33500
1'
0#
#33550
0'
1#
#33600
1'
0#
#33650
0'
1#
#33700
1'
0#
#33750
0'
1#
#33800
1'
0#
#33850
0'
1#
#33900
1'
0#
#33950
0'
1#
#34000
1'
0#
#34050
0'
1#
#34100
1'
0#
#34150
0'
1#
#34200
1'
0#
#34250
0'
1#
#34300
1'
0#
#34350
0'
1#
#34400
1'
0#
#34450
0'
1#
#34500
1'
0#
#34550
0'
1#
#34600
1'
0#
#34650
0'
1#
#34700
1'
0#
#34750
0'
1#
#34800
1'
0#
#34850
0'
1#
#34900
1'
0#
#34950
0'
1#
#35000
1'
0#
#35050
0'
1#
#35100
1'
0#
#35150
0'
1#
#35200
1'
0#
#35250
0'
1#
#35300
1'
0#
#35350
0'
1#
#35400
1'
0#
#35450
0'
1#
#35500
1'
0#
#35550
0'
1#
#35600
1'
0#
#35650
0'
1#
#35700
1'
0#
#35750
0'
1#
#35800
1'
0#
#35850
0'
1#
#35900
1'
0#
#35950
0'
1#
#36000
1'
0#
#36050
0'
1#
#36100
1'
0#
#36150
0'
1#
#36200
1'
0#
#36250
0'
1#
#36300
1'
0#
#36350
0'
1#
#36400
1'
0#
#36450
0'
1#
#36500
1'
0#
#36550
0'
1#
#36600
1'
0#
#36650
0'
1#
#36700
1'
0#
#36750
0'
1#
#36800
1'
0#
#36850
0'
1#
#36900
1'
0#
#36950
0'
1#
#37000
1'
0#
#37050
0'
1#
#37100
1'
0#
#37150
0'
1#
#37200
1'
0#
#37250
0'
1#
#37300
1'
0#
#37350
0'
1#
#37400
1'
0#
#37450
0'
1#
#37500
1'
0#
#37550
0'
1#
#37600
1'
0#
#37650
0'
1#
#37700
1'
0#
#37750
0'
1#
#37800
1'
0#
#37850
0'
1#
#37900
1'
0#
#37950
0'
1#
#38000
1'
0#
#38050
0'
1#
#38100
1'
0#
#38150
0'
1#
#38200
1'
0#
#38250
0'
1#
#38300
1'
0#
#38350
0'
1#
#38400
1'
0#
#38450
0'
1#
#38500
1'
0#
#38550
0'
1#
#38600
1'
0#
#38650
0'
1#
#38700
1'
0#
#38750
0'
1#
#38800
1'
0#
#38850
0'
1#
#38900
1'
0#
#38950
0'
1#
#39000
1'
0#
#39050
0'
1#
#39100
1'
0#
#39150
0'
1#
#39200
1'
0#
#39250
0'
1#
#39300
1'
0#
#39350
0'
1#
#39400
1'
0#
#39450
0'
1#
#39500
1'
0#
#39550
0'
1#
#39600
1'
0#
#39650
0'
1#
#39700
1'
0#
#39750
0'
1#
#39800
1'
0#
#39850
0'
1#
#39900
1'
0#
#39950
0'
1#
#40000
1'
0#
#40050
0'
1#
#40100
1'
0#
#40150
0'
1#
#40200
1'
0#
#40250
0'
1#
#40300
1'
0#
#40350
0'
1#
#40400
1'
0#
#40450
0'
1#
#40500
1'
0#
#40550
0'
1#
#40600
1'
0#
#40650
0'
1#
#40700
1'
0#
#40750
0'
1#
#40800
1'
0#
#40850
0'
1#
#40900
1'
0#
#40950
0'
1#
#41000
1'
0#
#41050
0'
1#
#41100
1'
0#
#41150
0'
1#
#41200
1'
0#
#41250
0'
1#
#41300
1'
0#
#41350
0'
1#
#41400
1'
0#
#41450
0'
1#
#41500
1'
0#
#41550
0'
1#
#41600
1'
0#
#41650
0'
1#
#41700
1'
0#
#41750
0'
1#
#41800
1'
0#
#41850
0'
1#
#41900
1'
0#
#41950
0'
1#
#42000
1'
0#
#42050
0'
1#
#42100
1'
0#
#42150
0'
1#
#42200
1'
0#
#42250
0'
1#
#42300
1'
0#
#42350
0'
1#
#42400
1'
0#
#42450
0'
1#
#42500
1'
0#
#42550
0'
1#
#42600
1'
0#
#42650
0'
1#
#42700
1'
0#
#42750
0'
1#
#42800
1'
0#
#42850
0'
1#
#42900
1'
0#
#42950
0'
1#
#43000
1'
0#
#43050
0'
1#
#43100
1'
0#
#43150
0'
1#
#43200
1'
0#
#43250
0'
1#
#43300
1'
0#
#43350
0'
1#
#43400
1'
0#
#43450
0'
1#
#43500
1'
0#
#43550
0'
1#
#43600
1'
0#
#43650
0'
1#
#43700
1'
0#
#43750
0'
1#
#43800
1'
0#
#43850
0'
1#
#43900
1'
0#
#43950
0'
1#
#44000
1'
0#
#44050
0'
1#
#44100
1'
0#
#44150
0'
1#
#44200
1'
0#
#44250
0'
1#
#44300
1'
0#
#44350
0'
1#
#44400
1'
0#
#44450
0'
1#
#44500
1'
0#
#44550
0'
1#
#44600
1'
0#
#44650
0'
1#
#44700
1'
0#
#44750
0'
1#
#44800
1'
0#
#44850
0'
1#
#44900
1'
0#
#44950
0'
1#
#45000
1'
0#
#45050
0'
1#
#45100
1'
0#
#45150
0'
1#
#45200
1'
0#
#45250
0'
1#
#45300
1'
0#
#45350
0'
1#
#45400
1'
0#
#45450
0'
1#
#45500
1'
0#
#45550
0'
1#
#45600
1'
0#
#45650
0'
1#
#45700
1'
0#
#45750
0'
1#
#45800
1'
0#
#45850
0'
1#
#45900
1'
0#
#45950
0'
1#
#46000
1'
0#
#46050
0'
1#
#46100
1'
0#
#46150
0'
1#
#46200
1'
0#
#46250
0'
1#
#46300
1'
0#
#46350
0'
1#
#46400
1'
0#
#46450
0'
1#
#46500
1'
0#
#46550
0'
1#
#46600
1'
0#
#46650
0'
1#
#46700
1'
0#
#46750
0'
1#
#46800
1'
0#
#46850
0'
1#
#46900
1'
0#
#46950
0'
1#
#47000
1'
0#
#47050
0'
1#
#47100
1'
0#
#47150
0'
1#
#47200
1'
0#
#47250
0'
1#
#47300
1'
0#
#47350
0'
1#
#47400
1'
0#
#47450
0'
1#
#47500
1'
0#
#47550
0'
1#
#47600
1'
0#
#47650
0'
1#
#47700
1'
0#
#47750
0'
1#
#47800
1'
0#
#47850
0'
1#
#47900
1'
0#
#47950
0'
1#
#48000
1'
0#
#48050
0'
1#
#48100
1'
0#
#48150
0'
1#
#48200
1'
0#
#48250
0'
1#
#48300
1'
0#
#48350
0'
1#
#48400
1'
0#
#48450
0'
1#
#48500
1'
0#
#48550
0'
1#
#48600
1'
0#
#48650
0'
1#
#48700
1'
0#
#48750
0'
1#
#48800
1'
0#
#48850
0'
1#
#48900
1'
0#
#48950
0'
1#
#49000
1'
0#
#49050
0'
1#
#49100
1'
0#
#49150
0'
1#
#49200
1'
0#
#49250
0'
1#
#49300
1'
0#
#49350
0'
1#
#49400
1'
0#
#49450
0'
1#
#49500
1'
0#
#49550
0'
1#
#49600
1'
0#
#49650
0'
1#
#49700
1'
0#
#49750
0'
1#
#49800
1'
0#
#49850
0'
1#
#49900
1'
0#
#49950
0'
1#
#50000
1'
0#
#50050
0'
1#
#50100
1'
0#
#50150
0'
1#
#50200
1'
0#
#50250
0'
1#
#50300
1'
0#
#50350
0'
1#
#50400
1'
0#
#50450
0'
1#
#50500
1'
0#
#50550
0'
1#
#50600
1'
0#
#50650
0'
1#
#50700
1'
0#
#50750
0'
1#
#50800
1'
0#
#50850
0'
1#
#50900
1'
0#
#50950
0'
1#
#51000
1'
0#
#51050
0'
1#
#51100
1'
0#
#51150
0'
1#
#51200
1'
0#
#51250
0'
1#
#51300
1'
0#
#51350
0'
1#
#51400
1'
0#
#51450
0'
1#
#51500
1'
0#
#51550
0'
1#
#51600
1'
0#
#51650
0'
1#
#51700
1'
0#
#51750
0'
1#
#51800
1'
0#
#51850
0'
1#
#51900
1'
0#
#51950
0'
1#
#52000
1'
0#
#52050
0'
1#
#52100
1'
0#
#52150
0'
1#
#52200
1'
0#
#52250
0'
1#
#52300
1'
0#
#52350
0'
1#
#52400
1'
0#
#52450
0'
1#
#52500
1'
0#
#52550
0'
1#
#52600
1'
0#
#52650
0'
1#
#52700
1'
0#
#52750
0'
1#
#52800
1'
0#
#52850
0'
1#
#52900
1'
0#
#52950
0'
1#
#53000
1'
0#
#53050
0'
1#
#53100
1'
0#
#53150
0'
1#
#53200
1'
0#
#53250
0'
1#
#53300
1'
0#
#53350
0'
1#
#53400
1'
0#
#53450
0'
1#
#53500
1'
0#
#53550
0'
1#
#53600
1'
0#
#53650
0'
1#
#53700
1'
0#
#53750
0'
1#
#53800
1'
0#
#53850
0'
1#
#53900
1'
0#
#53950
0'
1#
#54000
1'
0#
#54050
0'
1#
#54100
1'
0#
#54150
0'
1#
#54200
1'
0#
#54250
0'
1#
#54300
1'
0#
#54350
0'
1#
#54400
1'
0#
#54450
0'
1#
#54500
1'
0#
#54550
0'
1#
#54600
1'
0#
#54650
0'
1#
#54700
1'
0#
#54750
0'
1#
#54800
1'
0#
#54850
0'
1#
#54900
1'
0#
#54950
0'
1#
#55000
1'
0#
#55050
0'
1#
#55100
1'
0#
#55150
0'
1#
#55200
1'
0#
#55250
0'
1#
#55300
1'
0#
#55350
0'
1#
#55400
1'
0#
#55450
0'
1#
#55500
1'
0#
#55550
0'
1#
#55600
1'
0#
#55650
0'
1#
#55700
1'
0#
#55750
0'
1#
#55800
1'
0#
#55850
0'
1#
#55900
1'
0#
#55950
0'
1#
#56000
1'
0#
#56050
0'
1#
#56100
1'
0#
#56150
0'
1#
#56200
1'
0#
#56250
0'
1#
#56300
1'
0#
#56350
0'
1#
#56400
1'
0#
#56450
0'
1#
#56500
1'
0#
#56550
0'
1#
#56600
1'
0#
#56650
0'
1#
#56700
1'
0#
#56750
0'
1#
#56800
1'
0#
#56850
0'
1#
#56900
1'
0#
#56950
0'
1#
#57000
1'
0#
#57050
0'
1#
#57100
1'
0#
#57150
0'
1#
#57200
1'
0#
#57250
0'
1#
#57300
1'
0#
#57350
0'
1#
#57400
1'
0#
#57450
0'
1#
#57500
1'
0#
#57550
0'
1#
#57600
1'
0#
#57650
0'
1#
#57700
1'
0#
#57750
0'
1#
#57800
1'
0#
#57850
0'
1#
#57900
1'
0#
#57950
0'
1#
#58000
1'
0#
#58050
0'
1#
#58100
1'
0#
#58150
0'
1#
#58200
1'
0#
#58250
0'
1#
#58300
1'
0#
#58350
0'
1#
#58400
1'
0#
#58450
0'
1#
#58500
1'
0#
#58550
0'
1#
#58600
1'
0#
#58650
0'
1#
#58700
1'
0#
#58750
0'
1#
#58800
1'
0#
#58850
0'
1#
#58900
1'
0#
#58950
0'
1#
#59000
1'
0#
#59050
0'
1#
#59100
1'
0#
#59150
0'
1#
#59200
1'
0#
#59250
0'
1#
#59300
1'
0#
#59350
0'
1#
#59400
1'
0#
#59450
0'
1#
#59500
1'
0#
#59550
0'
1#
#59600
1'
0#
#59650
0'
1#
#59700
1'
0#
#59750
0'
1#
#59800
1'
0#
#59850
0'
1#
#59900
1'
0#
#59950
0'
1#
#60000
1'
0#
#60050
0'
1#
#60100
1'
0#
#60150
0'
1#
#60200
1'
0#
#60250
0'
1#
#60300
1'
0#
#60350
0'
1#
#60400
1'
0#
#60450
0'
1#
#60500
1'
0#
#60550
0'
1#
#60600
1'
0#
#60650
0'
1#
#60700
1'
0#
#60750
0'
1#
#60800
1'
0#
#60850
0'
1#
#60900
1'
0#
#60950
0'
1#
#61000
1'
0#
#61050
0'
1#
#61100
1'
0#
#61150
0'
1#
#61200
1'
0#
#61250
0'
1#
#61300
1'
0#
#61350
0'
1#
#61400
1'
0#
#61450
0'
1#
#61500
1'
0#
#61550
0'
1#
#61600
1'
0#
#61650
0'
1#
#61700
1'
0#
#61750
0'
1#
#61800
1'
0#
#61850
0'
1#
#61900
1'
0#
#61950
0'
1#
#62000
1'
0#
#62050
0'
1#
#62100
1'
0#
#62150
0'
1#
#62200
1'
0#
#62250
0'
1#
#62300
1'
0#
#62350
0'
1#
#62400
1'
0#
#62450
0'
1#
#62500
1'
0#
#62550
0'
1#
#62600
1'
0#
#62650
0'
1#
#62700
1'
0#
#62750
0'
1#
#62800
1'
0#
#62850
0'
1#
#62900
1'
0#
#62950
0'
1#
#63000
1'
0#
#63050
0'
1#
#63100
1'
0#
#63150
0'
1#
#63200
1'
0#
#63250
0'
1#
#63300
1'
0#
#63350
0'
1#
#63400
1'
0#
#63450
0'
1#
#63500
1'
0#
#63550
0'
1#
#63600
1'
0#
#63650
0'
1#
#63700
1'
0#
#63750
0'
1#
#63800
1'
0#
#63850
0'
1#
#63900
1'
0#
#63950
0'
1#
#64000
1'
0#
#64050
0'
1#
#64100
1'
0#
#64150
0'
1#
#64200
1'
0#
#64250
0'
1#
#64300
1'
0#
#64350
0'
1#
#64400
1'
0#
#64450
0'
1#
#64500
1'
0#
#64550
0'
1#
#64600
1'
0#
#64650
0'
1#
#64700
1'
0#
#64750
0'
1#
#64800
1'
0#
#64850
0'
1#
#64900
1'
0#
#64950
0'
1#
#65000
1'
0#
#65050
0'
1#
#65100
1'
0#
#65150
0'
1#
#65200
1'
0#
#65250
0'
1#
#65300
1'
0#
#65350
0'
1#
#65400
1'
0#
#65450
0'
1#
#65500
1'
0#
#65550
0'
1#
#65600
1'
0#
#65650
0'
1#
#65700
1'
0#
#65750
0'
1#
#65800
1'
0#
#65850
0'
1#
#65900
1'
0#
#65950
0'
1#
#66000
1'
0#
#66050
0'
1#
#66100
1'
0#
#66150
0'
1#
#66200
1'
0#
#66250
0'
1#
#66300
1'
0#
#66350
0'
1#
#66400
1'
0#
#66450
0'
1#
#66500
1'
0#
#66550
0'
1#
#66600
1'
0#
#66650
0'
1#
#66700
1'
0#
#66750
0'
1#
#66800
1'
0#
#66850
0'
1#
#66900
1'
0#
#66950
0'
1#
#67000
1'
0#
#67050
0'
1#
#67100
1'
0#
#67150
0'
1#
#67200
1'
0#
#67250
0'
1#
#67300
1'
0#
#67350
0'
1#
#67400
1'
0#
#67450
0'
1#
#67500
1'
0#
#67550
0'
1#
#67600
1'
0#
#67650
0'
1#
#67700
1'
0#
#67750
0'
1#
#67800
1'
0#
#67850
0'
1#
#67900
1'
0#
#67950
0'
1#
#68000
1'
0#
#68050
0'
1#
#68100
1'
0#
#68150
0'
1#
#68200
1'
0#
#68250
0'
1#
#68300
1'
0#
#68350
0'
1#
#68400
1'
0#
#68450
0'
1#
#68500
1'
0#
#68550
0'
1#
#68600
1'
0#
#68650
0'
1#
#68700
1'
0#
#68750
0'
1#
#68800
1'
0#
#68850
0'
1#
#68900
1'
0#
#68950
0'
1#
#69000
1'
0#
#69050
0'
1#
#69100
1'
0#
#69150
0'
1#
#69200
1'
0#
#69250
0'
1#
#69300
1'
0#
#69350
0'
1#
#69400
1'
0#
#69450
0'
1#
#69500
1'
0#
#69550
0'
1#
#69600
1'
0#
#69650
0'
1#
#69700
1'
0#
#69750
0'
1#
#69800
1'
0#
#69850
0'
1#
#69900
1'
0#
#69950
0'
1#
#70000
1'
0#
#70050
0'
1#
#70100
1'
0#
#70150
0'
1#
#70200
1'
0#
#70250
0'
1#
#70300
1'
0#
#70350
0'
1#
#70400
1'
0#
#70450
0'
1#
#70500
1'
0#
#70550
0'
1#
#70600
1'
0#
#70650
0'
1#
#70700
1'
0#
#70750
0'
1#
#70800
1'
0#
#70850
0'
1#
#70900
1'
0#
#70950
0'
1#
#71000
1'
0#
#71050
0'
1#
#71100
1'
0#
#71150
0'
1#
#71200
1'
0#
#71250
0'
1#
#71300
1'
0#
#71350
0'
1#
#71400
1'
0#
#71450
0'
1#
#71500
1'
0#
#71550
0'
1#
#71600
1'
0#
#71650
0'
1#
#71700
1'
0#
#71750
0'
1#
